<?xml version="1.0" encoding="UTF-8"?>
<bulkPmMrDataFile>
    <fileHeader fileFormatVersion="1.0.0" reportTime="2016-11-29T14:07:24.670" startTime="2016-11-29T13:45:00.000" endTime="2016-11-29T14:00:00.000" period="15" jobid="1"/>
    <eNB userLabel="CDT6318" id="464787">
        <measurement mrName="MR.RSRP">
            <smr>MR.RSRP.00 MR.RSRP.01 MR.RSRP.02 MR.RSRP.03 MR.RSRP.04 MR.RSRP.05 MR.RSRP.06 MR.RSRP.07 MR.RSRP.08 MR.RSRP.09 MR.RSRP.10 MR.RSRP.11 MR.RSRP.12 MR.RSRP.13 MR.RSRP.14 MR.RSRP.15 MR.RSRP.16 MR.RSRP.17 MR.RSRP.18 MR.RSRP.19 MR.RSRP.20 MR.RSRP.21 MR.RSRP.22 MR.RSRP.23 MR.RSRP.24 MR.RSRP.25 MR.RSRP.26 MR.RSRP.27 MR.RSRP.28 MR.RSRP.29 MR.RSRP.30 MR.RSRP.31 MR.RSRP.32 MR.RSRP.33 MR.RSRP.34 MR.RSRP.35 MR.RSRP.36 MR.RSRP.37 MR.RSRP.38 MR.RSRP.39 MR.RSRP.40 MR.RSRP.41 MR.RSRP.42 MR.RSRP.43 MR.RSRP.44 MR.RSRP.45 MR.RSRP.46 MR.RSRP.47</smr>
            <object id="118985535" MmeUeS1apId="37821428" MmeGroupId="4218" MmeCode="0" TimeStamp="2016-11-29T13:39:12.960">
                <v>0 0 0 0 0 0 0 0 0 0 0 0 0 0 0 0 0 0 0 0 0 0 0 0 0 0 0 0 0 0 0 0 0 0 0 0 0 0 0 0 0 0 0 0 0 0 0 0</v>
            </object>
        </measurement>
    </eNB>
  </bulkPmMrDataFile>